{
  "scenes": {
    "background": "走进办公室后，[小王]看了一眼自己的工作任务表，叹了口气：",
    "description": "有时候真觉得忙得没时间喘气，真不理解你怎么还能保持这么积极。",
    "options": [
      {
        "text": "1. 可能是因为我比较享受忙碌带来的成就感吧。",
        "scores": {
          "情绪侦查力": 4,
          "情绪掌控力": 3,
          "人际平衡术": 3,
          "沟通表达力": 4,
          "社交得体度": 3
        },
        "analysis": "你的回答展示了你对忙碌生活的正面态度，表现了较好的情绪侦查力和沟通表达力。"
      },
      {
        "text": "2. 哈哈，可能是我比较能自娱自乐吧。",
        "scores": {
          "情绪侦查力": 3,
          "情绪掌控力": 3,
          "人际平衡术": 2,
          "沟通表达力": 3,
          "社交得体度": 2
        },
        "analysis": "你的回答显得轻松幽默，但在人际平衡术和社交得体度上稍显不足。"
      },
      {
        "text": "3. 我觉得找到工作的意义和目标，这样会更容易保持积极。",
        "scores": {
          "情绪侦查力": 4,
          "情绪掌控力": 4,
          "人际平衡术": 4,
          "沟通表达力": 3,
          "社交得体度": 4
        },
        "analysis": "你的回答展示了你对工作的深思和目标感，表现了较好的情绪侦查力和人际平衡术。"
      }
    ]
  }
}