{
  "scenes": {
    "background": "[小李]听完你的回答，露出一丝苦笑，对[小王]说：",
    "description": "不过，[小王]，人家说得也有道理啊，我们还是别互相较劲了。你怎么看？",
    "options": [
      {
        "text": "1. 其实公司里竞争是难免的，但我们也可以合作共赢啊。",
        "scores": {
          "情绪侦查力": 4,
          "情绪掌控力": 3,
          "人际平衡术": 4,
          "沟通表达力": 3,
          "社交得体度": 3
        },
        "analysis": "你的回答展示了积极合作的态度，表现了较好的人际平衡术和情绪侦查力，但情绪掌控力和沟通表达力稍显不足。"
      },
      {
        "text": "2. 竞争的确存在，但最终的目的是为了更好的业绩和发展。",
        "scores": {
          "情绪侦查力": 3,
          "情绪掌控力": 3,
          "人际平衡术": 2,
          "沟通表达力": 4,
          "社交得体度": 2
        },
        "analysis": "你的回答强调了目标和业绩的重要性，展现了较好的沟通表达力，但在人际平衡术和社交得体度上稍显不足。"
      },
      {
        "text": "3. 我觉得有时候适当的竞争能激发我们的潜力，不过也不应该过分看重。",
        "scores": {
          "情绪侦查力": 4,
          "情绪掌控力": 4,
          "人际平衡术": 3,
          "沟通表达力": 3,
          "社交得体度": 3
        },
        "analysis": "你的回答显得中肯，平衡了竞争和合作的关系，表现了较好的情绪侦查力和情绪掌控力。"
      }
    ]
  }
}