{
  "scenes": {
    "background": "你刚刚解释了你对工作的热情，[小李]突然转过身对你说：",
    "description": "工作热情是好事，但你这样是不是有点过了啊？",
    "options": [
      {
        "text": "1. 过了吗？我只是想尽快融入团队，毕竟咱们都是一条船上的。",
        "scores": {
          "情绪侦查力": 3,
          "情绪掌控力": 3,
          "人际平衡术": 4,
          "沟通表达力": 4,
          "社交得体度": 3
        },
        "analysis": "你通过强调团队合作来表达自己的动机，但在情绪侦查力上稍显不足。"
      },
      {
        "text": "2. 每个人的方式不一样，这样让我感到有动力。",
        "scores": {
          "情绪侦查力": 3,
          "情绪掌控力": 4,
          "人际平衡术": 3,
          "沟通表达力": 4,
          "社交得体度": 3
        },
        "analysis": "你展示了自信和对自己方式的认可，但在人际平衡术上稍显欠缺。"
      },
      {
        "text": "3. 也许吧，不过我相信只要做好自己的工作，最终都会有回报。",
        "scores": {
          "情绪侦查力": 4,
          "情绪掌控力": 3,
          "人际平衡术": 3,
          "沟通表达力": 3,
          "社交得体度": 4
        },
        "analysis": "你通过冷静且理性的方式回应展示了较好的情绪侦查力，但在沟通表达力上稍显不足。"
      }
    ]
  }
}