{
  "scenes": {
    "background": "你刚刚回答了是否过于热情的问题，[小王]接着说：",
    "description": "那你觉得我们平时工作够努力吗？",
    "options": [
      {
        "text": "1. 当然啊，我觉得你们都非常敬业，我也希望能向你们学习。",
        "scores": {
          "情绪侦查力": 3,
          "情绪掌控力": 4,
          "人际平衡术": 4,
          "沟通表达力": 3,
          "社交得体度": 3
        },
        "analysis": "你通过赞扬同事来表达自己的敬意和愿望，但在情绪侦查力上稍显不足。"
      },
      {
        "text": "2. 每个人都有不同的工作节奏，只要结果好就行。",
        "scores": {
          "情绪侦查力": 4,
          "情绪掌控力": 3,
          "人际平衡术": 3,
          "沟通表达力": 3,
          "社交得体度": 3
        },
        "analysis": "你通过强调结果导向展示了较好的情绪侦查力，但在人际平衡术上稍显欠缺。"
      },
      {
        "text": "3. 说实话，我觉得大家有时候可以更有效率一点。",
        "scores": {
          "情绪侦查力": 3,
          "情绪掌控力": 2,
          "人际平衡术": 3,
          "沟通表达力": 4,
          "社交得体度": 3
        },
        "analysis": "你展示了诚实和直率的态度，但可能会在情绪掌控力上显得欠缺。"
      }
    ]
  }
}