{
  "scenes": {
    "background": "你们在茶水间和主管聊着昨天会议的反馈。[小王]和[小李]也加入了讨论。就在这时，[小王]提到了公司的工作安排。",
    "description": "[小王]笑着问：",
    "options": [
      {
        "text": "1.小王：大家觉得最近的工作安排是否合理？",
        "scores": {
          "情绪侦查力": 3,
          "情绪掌控力": 4,
          "人际平衡术": 2,
          "沟通表达力": 3,
          "社交得体度": 4
        },
        "analysis": "你敏锐地提出了一个可能存在的问题，展示了较好的情绪掌控力和社交得体度，但在人际平衡术上略有不足。"
      },
      {
        "text": "2.小王：最近工作安排看起来有点紧，大家都能适应吗？",
        "scores": {
          "情绪侦查力": 4,
          "情绪掌控力": 3,
          "人际平衡术": 3,
          "沟通表达力": 2,
          "社交得体度": 3
        },
        "analysis": "你关注同事们的感受，表现了较好的情绪侦查力，但沟通表达力稍有不足。"
      },
      {
        "text": "3.小王：其实工作安排得紧一些也挺好的，可以锻炼我们的能力。",
        "scores": {
          "情绪侦查力": 3,
          "情绪掌控力": 3,
          "人际平衡术": 4,
          "沟通表达力": 3,
          "社交得体度": 3
        },
        "analysis": "你对工作安排表示了支持，表现了较好的人际平衡术，但其他维度表现中等。"
      }
    ]
  }
}