{
  "scenes": {
    "background": "[小王]一听你说要分享有趣的事情，凑近了一步，带着些许挑衅的笑意说：",
    "description": "你有啥有趣的事情能比得上[小李]那次穿错鞋子开会的糗事吗？",
    "options": [
      {
        "text": "1.哈哈，其实也没那么精彩啦，但我曾在一次客户会议上误把咖啡洒到客户的手提包里，结果惹得客户大笑。",
        "scores": {
          "情绪侦查力": 4,
          "情绪掌控力": 4,
          "人际平衡术": 4,
          "沟通表达力": 4,
          "社交得体度": 4
        },
        "analysis": "你用幽默和自嘲的方式回应了挑衅，展示了良好的情绪侦查力和人际平衡术，同时表现出较高的沟通表达力。"
      },
      {
        "text": "2.说起来，你们是在怀疑我没啥有趣的事吗？",
        "scores": {
          "情绪侦查力": 3,
          "情绪掌控力": 2,
          "人际平衡术": 2,
          "沟通表达力": 2,
          "社交得体度": 2
        },
        "analysis": "你有些防备和不悦，虽然展示了情绪侦查，但在人际平衡术和情绪掌控力方面显得欠缺。"
      },
      {
        "text": "3.哎呀，每个人都有些小趣事，不过我可没像[小李]那样穿错鞋子开会。",
        "scores": {
          "情绪侦查力": 3,
          "情绪掌控力": 3,
          "人际平衡术": 3,
          "沟通表达力": 3,
          "社交得体度": 3
        },
        "analysis": "你的回应比较中性，虽然化解了尴尬，但在情绪侦查和人际平衡术方面表现平平。"
      }
    ]
  }
}