{
  "scenes": {
    "background": "小王看你一脸认真，说了一句：",
    "description": "学习是好事，但你觉得单凭这种态度就能成功吗？",
    "options": [
      {
        "text": "1. 当然不是，只是态度端正是基础，努力和机会同样重要。",
        "scores": {
          "情绪侦查力": 4,
          "情绪掌控力": 4,
          "人际平衡术": 4,
          "沟通表达力": 5,
          "社交得体度": 5
        },
        "analysis": "你的回答综合了态度与其他因素，展现了平衡的看法和良好的沟通表达力。"
      },
      {
        "text": "2. 态度固然重要，但具体如何做到，还得一步一步来。",
        "scores": {
          "情绪侦查力": 3,
          "情绪掌控力": 3,
          "人际平衡术": 4,
          "沟通表达力": 4,
          "社交得体度": 3
        },
        "analysis": "你的回答体现了实际行动的重视，但在情绪掌控力上稍显不足。"
      },
      {
        "text": "3. 成功从来都是靠运气和资源，不是仅靠态度。",
        "scores": {
          "情绪侦查力": 2,
          "情绪掌控力": 2,
          "人际平衡术": 3,
          "沟通表达力": 3,
          "社交得体度": 2
        },
        "analysis": "你的回答有些消极，虽然展示了对现实的认知，但在情绪掌控力和社交得体度上较为欠缺。"
      }
    ]
  }
}