{
  "scenes": {
    "background": "[老板]满意地点了点头，正准备说什么，这时电梯到达了你们的楼层。你们三人走出电梯，[小王]突然对你说：",
    "description": "对了，你还不知道我们的办公室在哪吧，我带你去吧。",
    "options": [
      {
        "text": "1. 谢谢你，[小王]，我正好有点迷路了。",
        "scores": {
          "情绪侦查力": 4,
          "情绪掌控力": 4,
          "人际平衡术": 4,
          "沟通表达力": 4,
          "社交得体度": 4
        },
        "analysis": "你礼貌地接受了同事的帮助，表现了较高的情绪侦查力和社交得体度。"
      },
      {
        "text": "2. 不用了，[小王]，我刚刚已经看过地图了，可以自己找到。",
        "scores": {
          "情绪侦查力": 3,
          "情绪掌控力": 3,
          "人际平衡术": 3,
          "沟通表达力": 3,
          "社交得体度": 3
        },
        "analysis": "你表现了独立性，但在人际平衡术上表现稍显一般。"
      },
      {
        "text": "3. 你是不是觉得我找不到路？还是你对我的能力有些质疑？",
        "scores": {
          "情绪侦查力": 2,
          "情绪掌控力": 2,
          "人际平衡术": 2,
          "沟通表达力": 2,
          "社交得体度": 2
        },
        "analysis": "你的回答带有防御和质疑意味，表现了较低的人际平衡术和社交得体度。"
      }
    ]
  }
}