{
  "scenes": {
    "background": "你和同事[小王]、[小李]在茶水间讨论项目进展时，你说只要我们尽力了，就不怕被责怪。",
    "description": "[小李]笑着说道：你这话倒轻松，万一最后被推出来背锅可怎么办？",
    "options": [
      {
        "text": "1.我们是一个团队，不应该有人单独背锅。",
        "scores": {
          "情绪侦查力": 3,
          "情绪掌控力": 4,
          "人际平衡术": 4,
          "沟通表达力": 3,
          "社交得体度": 3
        },
        "analysis": "你强调了团队精神，展示了对团队的支持和较强的情绪掌控力，但在沟通表达力上稍显欠缺。"
      },
      {
        "text": "2.那我们更要做好每一步，不给别人推锅的机会。",
        "scores": {
          "情绪侦查力": 4,
          "情绪掌控力": 3,
          "人际平衡术": 3,
          "沟通表达力": 4,
          "社交得体度": 3
        },
        "analysis": "你展示了积极主动的态度和对工作的高度责任感，体现了较强的情绪侦查力和沟通表达力。"
      },
      {
        "text": "3.说得对，大家还是要各尽其职，谁也别想甩锅。",
        "scores": {
          "情绪侦查力": 2,
          "情绪掌控力": 3,
          "人际平衡术": 3,
          "沟通表达力": 2,
          "社交得体度": 2
        },
        "analysis": "你虽然表达了自己的观点，但在情绪侦查力和社交得体度上稍显不足。"
      }
    ]
  }
}