{
  "scenes": {
    "background": "在走廊上的对话结束后，[小王]、[小李]和你走到休息区继续讨论新的策略。",
    "description": "[小李]说：既然我们要重新考虑策略，那具体有什么新的想法吗？",
    "options": [
      {
        "text": "1.我觉得我们可以尝试一些创新的方法，比如引入一些新技术来提升效率。",
        "scores": {
          "情绪侦查力": 4,
          "情绪掌控力": 3,
          "人际平衡术": 3,
          "沟通表达力": 4,
          "社交得体度": 3
        },
        "analysis": "你提出了具体的建议，展示了较高的情绪侦查力和沟通表达力，但在人际平衡术上稍显欠缺。"
      },
      {
        "text": "2.我们可以先做一个小规模的试验项目，如果成功再大规模推广。",
        "scores": {
          "情绪侦查力": 3,
          "情绪掌控力": 4,
          "人际平衡术": 3,
          "沟通表达力": 3,
          "社交得体度": 4
        },
        "analysis": "你表现出稳健的策略，展示了较好的情绪掌控力和社交得体度，但在情绪侦查力上稍有不足。"
      },
      {
        "text": "3.我觉得我们应该先听听大家的意见，然后再决定具体方案。",
        "scores": {
          "情绪侦查力": 3,
          "情绪掌控力": 3,
          "人际平衡术": 4,
          "沟通表达力": 3,
          "社交得体度": 3
        },
        "analysis": "你强调了团队合作的重要性，表现了较好的情绪掌控力和人际平衡术，但在情绪侦查力和社交得体度上稍显平淡。"
      }
    ]
  }
}